<?xml version="1.0"?>
<templates>
	<models>
		<!-- A fully defined template -->
		<intelligence name="base">
			<signature type="visual" level="likely">
				<!-- Possible Stances are: 
				     deployed, transit, offense, 
				     hasty defense, prepared defense, 
				     service
				     
				     Possible activities:
				     transit, combat, service, idle
				  -->
				  <very_likely>combat,transit</very_likely>
				  <neutral>deployed,hasty defense</neutral>
				  <unlikely>prepared defense</unlikely>
			</signature>
			<signature type="thermal" sameas="visual"/>
			<signature type="sound" level="unlikely">
				<likely>transit</likely>
				<very_likely>combat</very_likely>
			</signature>
		</intelligence>
		
		<!-- Static LOGPAC -->
		<intelligence name="LOGPAC">
			<signature type="visual" level="unlikely"/>
		</intelligence>
	</models>
</templates>
